roadie/__init__.py
roadie/resources/__init__.py
roadie/resources/estimates.py
roadie/resources/shipments.py
roadie/types.py
python_roadie-1.0.1.dist-info/METADATA
python_roadie-1.0.1.dist-info/WHEEL
python_roadie-1.0.1.dist-info/RECORD
