Metadata-Version: 2.1
Name: python-roadie
Version: 1.0.1
Summary: Python client for roadie API
Home-page: https://github.com/fbanu95/python-roadie
Keywords: roadie-api,python-client,roadie-python-client
Author: Farhath Banu
Author-email: farhath@proxyroot.com
Requires-Python: >=3.7,<4.0
Classifier: Environment :: Console
Classifier: Operating System :: OS Independent
Classifier: Programming Language :: Python :: 3
Classifier: Programming Language :: Python :: 3.7
Classifier: Programming Language :: Python :: 3.8
Classifier: Programming Language :: Python :: 3.9
Classifier: Programming Language :: Python :: 3.10
Classifier: Programming Language :: Python :: 3.11
Classifier: Topic :: Software Development :: Documentation
Classifier: Topic :: Software Development :: Libraries :: Python Modules
Requires-Dist: pydantic (>=1.10.2,<2.0.0)
Requires-Dist: requests (>=2.28.1,<3.0.0)
Project-URL: Repository, https://github.com/fbanu95/python-roadie
